tet/fanstatic/__init__.py
tet.fanstatic-0.1.dist-info/DESCRIPTION.rst
tet.fanstatic-0.1.dist-info/METADATA
tet.fanstatic-0.1.dist-info/RECORD
tet.fanstatic-0.1.dist-info/WHEEL
tet.fanstatic-0.1.dist-info/metadata.json
tet.fanstatic-0.1.dist-info/top_level.txt
